{
  "id": "pe-nl-2043110-1",
  "type": "statute",
  "title": "Ley que deroga la Ley 30636, Ley que Crea el Seguro Obligatorio del Pescador Artesanal (SOPA)",
  "short_name": "N° 31428",
  "status": "in_force",
  "issued_date": "2022-02-26",
  "in_force_date": "2022-02-26",
  "url": "https://busquedas.elperuano.pe/dispositivo/NL/2043110-1",
  "description": "LEY | N° 31428 | Ley que deroga la Ley 30636, Ley que Crea el Seguro Obligatorio del Pescador Artesanal (SOPA)",
  "provisions": [
    {
      "provision_ref": "artunico",
      "section": "UNICO",
      "title": "Artículo UNICO.- Objeto de la Ley",
      "content": "Se deroga la Ley 30636, Ley que Crea el Seguro Obligatorio del Pescador Artesanal (SOPA). Comuníquese al señor Presidente de la República para su promulgación. En Lima, a los ocho días del mes de febrero de dos mil veintidós. MARÍA DEL CARMEN ALVA PRIETO Presidenta del Congreso de la República LADY MERCEDES CAMONES SORIANO Primera Vicepresidenta del Congreso de la República AL SEÑOR PRESIDENTE DE LA REPÚBLICA POR TANTO: Mando se publique y cumpla. Dado en la Casa de Gobierno, en Lima, a los veinticinco días del mes de febrero del año dos mil veintidós. JOSÉ PEDRO CASTILLO TERRONES Presidente de la República ANÍBAL TORRES VÁSQUEZ Presidente del Consejo de Ministros"
    }
  ],
  "definitions": []
}