{
  "id": "pe-nl-1866220-11",
  "type": "statute",
  "title": "Decreto de Urgencia que modifica el Anexo del Decreto de Urgencia N° 035-2020",
  "short_name": "N° 054-2020",
  "status": "in_force",
  "issued_date": "2020-05-11",
  "in_force_date": "2020-05-11",
  "url": "https://busquedas.elperuano.pe/dispositivo/NL/1866220-11",
  "description": "DECRETO DE URGENCIA | N° 054-2020 | Decreto de Urgencia que modifica el Anexo del Decreto de Urgencia N° 035-2020",
  "provisions": [
    {
      "provision_ref": "art1",
      "section": "1",
      "title": "Artículo 1.- Incorporación en el Anexo del artículo 18 del Decreto de Urgencia Nº 035-2020",
      "content": "Incorpórese dentro del anexo del artículo 18 del Decreto Urgencia Nº 035-2020, que dicta medidas complementarias para reforzar los sistemas de prevención, control, vigilancia y respuesta sanitaria para la atención de la emergencia producida por el COVID-19, el siguiente texto: (…) HOSPITAL II - 2 CESAR GARAYAR GARCÍA - Iquitos EQUIPOS BIOMEDICOS CANTIDAD (…) Central de Oxigeno Medicinal 1 (…)"
    },
    {
      "provision_ref": "art2",
      "section": "2",
      "title": "Artículo 2.- Vigencia",
      "content": "El presente Decreto de Urgencia tiene vigencia hasta el 31 de diciembre de 2020."
    },
    {
      "provision_ref": "art3",
      "section": "3",
      "title": "Artículo 3.- Refrendo",
      "content": "El presente Decreto de Urgencia es refrendado por el Presidente del Consejo de Ministros, por la Ministra de Trabajo y Promoción del Empleo, por la Ministra de Energía y Minas, por el Ministro de Transportes y Comunicaciones, por el Ministro de Comercio Exterior y Turismo, por el Ministro de Salud, y por la Ministra de Economía y Finanzas. Dado en la Casa de Gobierno, en Lima, a los diez días del mes de mayo del año dos mil veinte. MARTÍN ALBERTO VIZCARRA CORNEJO Presidente de la República VICENTE ANTONIO ZEBALLOS SALINAS Presidente del Consejo de Ministros EDGAR M. VÁSQUEZ VELA Ministro de Comercio Exterior y Turismo MARÍA ANTONIETA ALVA LUPERDI Ministra de Economía y Finanzas SUSANA VILCA ACHATA Ministra de Energía y Minas VÍCTOR ZAMORA MESÍA Ministro de Salud SYLVIA E. CÁCERES PIZARRO Ministra de Trabajo y Promoción del Empleo CARLOS LOZADA CONTRERAS Ministro de Transportes y Comunicaciones"
    }
  ],
  "definitions": []
}