{
  "id": "pe-nl-2297823-1",
  "type": "statute",
  "title": "Ley que declara de interés nacional la creación de la Universidad Nacional de Sechura en la provincia de Sechura del departamento de Piura",
  "short_name": "N° 32057",
  "status": "in_force",
  "issued_date": "2024-06-14",
  "in_force_date": "2024-06-14",
  "url": "https://busquedas.elperuano.pe/dispositivo/NL/2297823-1",
  "description": "LEY | N° 32057 | Ley que declara de interés nacional la creación de la Universidad Nacional de Sechura en la provincia de Sechura del departamento de Piura",
  "provisions": [],
  "definitions": []
}