{
  "id": "pe-nl-655237-2",
  "type": "statute",
  "title": "Autorizan Transferencia de Partidas en el Presupuesto del Sector Público para el Año Fiscal 2011, a favor de diez (10) Gobiernos Regionales y once (11) Gobiernos Locales, para el financiamiento de proyectos de inversión y fortalecimiento de la capacidad resolutiva de establecimientos de salud",
  "short_name": "N° 029-2011",
  "status": "in_force",
  "issued_date": "2011-06-19",
  "in_force_date": "2011-06-19",
  "url": "https://busquedas.elperuano.pe/dispositivo/NL/655237-2",
  "description": "DECRETO DE URGENCIA | N° 029-2011 | Autorizan Transferencia de Partidas en el Presupuesto del Sector Público para el Año Fiscal 2011, a favor de diez (10) Gobiernos Regionales y once (11) Gobiernos Locales, para el financiamiento de proyectos de inversión y fortalecimiento de la capacidad resolutiva de establecimientos de salud",
  "provisions": [],
  "definitions": []
}