{
  "id": "pe-nl-2357993-4",
  "type": "statute",
  "title": "Ley que prorroga la vigencia de los beneficios tributarios del Decreto Legislativo 783, que aprueba la norma sobre devolución de impuestos que gravan las adquisiciones con donaciones del exterior e importaciones de misiones diplomáticas y otros",
  "short_name": "N° 32220",
  "status": "in_force",
  "issued_date": "2024-12-29",
  "in_force_date": "2024-12-29",
  "url": "https://busquedas.elperuano.pe/dispositivo/NL/2357993-4",
  "description": "LEY | N° 32220 | Ley que prorroga la vigencia de los beneficios tributarios del Decreto Legislativo 783, que aprueba la norma sobre devolución de impuestos que gravan las adquisiciones con donaciones del exterior e importaciones de misiones diplomáticas y otros",
  "provisions": [],
  "definitions": []
}