{
  "id": "pe-nl-145358-8",
  "type": "statute",
  "title": "Ley de promoción del desarrollo sostenible de servicios turísticos en los bienes inmuebles, integrantes del Patrimonio Cultural de la Nación",
  "short_name": "N° 29164",
  "status": "in_force",
  "issued_date": "2007-12-20",
  "in_force_date": "2007-12-20",
  "url": "https://busquedas.elperuano.pe/dispositivo/NL/145358-8",
  "description": "LEY | N° 29164 | Ley de promoción del desarrollo sostenible de servicios turísticos en los bienes inmuebles, integrantes del Patrimonio Cultural de la Nación",
  "provisions": [],
  "definitions": []
}