{
  "id": "pe-nl-634773-1",
  "type": "statute",
  "title": "Ley que establece plazo excepcional para la publicación de Ordenanzas que aprueban Arbitrios Municipales",
  "short_name": "N° 29679",
  "status": "in_force",
  "issued_date": "2011-04-30",
  "in_force_date": "2011-04-30",
  "url": "https://busquedas.elperuano.pe/dispositivo/NL/634773-1",
  "description": "LEY | N° 29679 | Ley que establece plazo excepcional para la publicación de Ordenanzas que aprueban Arbitrios Municipales",
  "provisions": [],
  "definitions": []
}